README.rst
setup.py
bitlurker_client.egg-info/PKG-INFO
bitlurker_client.egg-info/SOURCES.txt
bitlurker_client.egg-info/dependency_links.txt
bitlurker_client.egg-info/not-zip-safe
bitlurker_client.egg-info/top_level.txt
foo/__init__.py